smartcite_site/__init__.py
smartcite_site/main.py
smartcite_site/prompts.py
smartcite_site-2025.12.20175753.dist-info/METADATA
smartcite_site-2025.12.20175753.dist-info/WHEEL
smartcite_site-2025.12.20175753.dist-info/top_level.txt
smartcite_site-2025.12.20175753.dist-info/RECORD
