Metadata-Version: 2.4
Name: smartcite_site
Version: 2025.12.20175753
Summary: **Problem:**  
Author-email: smartcite_site <hi@eugene.plus>
License: MIT
Project-URL: Homepage, https://github.com/chigwell/smartcite_site
Requires-Python: >=3.9
Requires-Dist: langchain-llm7>=0.0.0
Requires-Dist: llmatch-messages>=0.0.0
Requires-Dist: langchain-core>=0.3.0
